noseapp_requests/__init__.py
noseapp_requests/base.py
noseapp_requests/config.py
noseapp_requests/urlbuilder.py
noseapp_requests-0.0.1.dist-info/DESCRIPTION.rst
noseapp_requests-0.0.1.dist-info/METADATA
noseapp_requests-0.0.1.dist-info/metadata.json
noseapp_requests-0.0.1.dist-info/pbr.json
noseapp_requests-0.0.1.dist-info/RECORD
noseapp_requests-0.0.1.dist-info/top_level.txt
noseapp_requests-0.0.1.dist-info/WHEEL
