Metadata-Version: 2.0
Name: noseapp-requests
Version: 0.0.1
Summary: requests extension for noseapp lib
Home-page: https://github.com/brannt/noseapp_requests
Author: Artem Gorokhov
Author-email: a.gorohov@corp.mail.ru
License: UNKNOWN
Keywords: noseapp requests testing
Platform: any
Classifier: Development Status :: 3 - Alpha
Classifier: Intended Audience :: Developers
Classifier: Topic :: Software Development :: Testing
Classifier: Programming Language :: Python :: 2
Classifier: Programming Language :: Python :: 2.6
Classifier: Programming Language :: Python :: 2.7
Requires-Dist: noseapp
Requires-Dist: requests (==2.6.0)
Provides-Extra: doc
Requires-Dist: Sphinx; extra == 'doc'
